CHANGELOG.md
LICENSE
MANIFEST.in
README.md
setup.cfg
setup.py
data/MRBrainS13DataNii/.gitkeep
dltk/__init__.py
dltk/utils.py
dltk/version.py
dltk.egg-info/PKG-INFO
dltk.egg-info/SOURCES.txt
dltk.egg-info/dependency_links.txt
dltk.egg-info/requires.txt
dltk.egg-info/top_level.txt
dltk/core/__init__.py
dltk/core/activations.py
dltk/core/losses.py
dltk/core/metrics.py
dltk/core/residual_unit.py
dltk/core/upsample.py
dltk/io/__init__.py
dltk/io/abstract_reader.py
dltk/io/augmentation.py
dltk/io/preprocessing.py
dltk/networks/__init__.py
dltk/networks/autoencoder/__init__.py
dltk/networks/autoencoder/convolutional_autoencoder.py
dltk/networks/gan/__init__.py
dltk/networks/gan/dcgan.py
dltk/networks/regression_classification/__init__.py
dltk/networks/regression_classification/resnet.py
dltk/networks/segmentation/__init__.py
dltk/networks/segmentation/deepmedic.py
dltk/networks/segmentation/fcn.py
dltk/networks/segmentation/unet.py
dltk/networks/super_resolution/__init__.py
dltk/networks/super_resolution/simple_super_resolution.py
examples/applications/IXI_HH_DCGAN/README.md
examples/applications/IXI_HH_DCGAN/reader.py
examples/applications/IXI_HH_DCGAN/train.py
examples/applications/IXI_HH_age_regression_resnet/README.md
examples/applications/IXI_HH_age_regression_resnet/deploy.py
examples/applications/IXI_HH_age_regression_resnet/reader.py
examples/applications/IXI_HH_age_regression_resnet/train.py
examples/applications/IXI_HH_representation_learning_cae/README.md
examples/applications/IXI_HH_representation_learning_cae/reader.py
examples/applications/IXI_HH_representation_learning_cae/train.py
examples/applications/IXI_HH_sex_classification_resnet/README.md
examples/applications/IXI_HH_sex_classification_resnet/deploy.py
examples/applications/IXI_HH_sex_classification_resnet/reader.py
examples/applications/IXI_HH_sex_classification_resnet/train.py
examples/applications/IXI_HH_superresolution/README.md
examples/applications/IXI_HH_superresolution/reader.py
examples/applications/IXI_HH_superresolution/train.py
examples/applications/MRBrainS13_tissue_segmentation/README.md
