Metadata-Version: 1.1
Name: dltk
Version: 0.2.1
Summary: Deep Learning Toolkit for Medical Image Analysis
Home-page: https://dltk.github.io
Author: DLTK contributors
Author-email: UNKNOWN
License: Apache License 2.0
Keywords: machine learning,tensorflow,deep learning,biomedical imaging
Platform: UNKNOWN
Classifier: Intended Audience :: Developers
Classifier: Intended Audience :: Education
Classifier: Intended Audience :: Science/Research
Classifier: License :: OSI Approved :: Apache Software License
Classifier: Operating System :: POSIX :: Linux
Classifier: Operating System :: MacOS :: MacOS X
Classifier: Operating System :: Microsoft :: Windows
Classifier: Programming Language :: Python :: 2.7
Classifier: Programming Language :: Python :: 3.4
